examples/__init__.py
examples/image_processing_workflow.py
swafe/__init__.py
swafe/activity.py
swafe/cli.py
swafe/daemon.py
swafe/helpers.py
swafe/lib.py
swafe/poller.py
swafe/runner.py
swafe/task.py
swafe/workflow.py
swafe/exceptions/__init__.py
swafe/exceptions/activity_failed.py
swafe/exceptions/malformed_task.py
swafe/exceptions/workflow_failed.py
swafe/tests/__init__.py
swafe/tests/mocker.py
swafe/tests/test_cli.py
swafe/tests/test_poller.py
swafer-0.0.2.dist-info/DESCRIPTION.rst
swafer-0.0.2.dist-info/METADATA
swafer-0.0.2.dist-info/RECORD
swafer-0.0.2.dist-info/WHEEL
swafer-0.0.2.dist-info/entry_points.txt
swafer-0.0.2.dist-info/metadata.json
swafer-0.0.2.dist-info/top_level.txt
