Metadata-Version: 2.0
Name: swafer
Version: 0.0.2
Summary: A python library for orchestrating AWS SWF workflows, extended on Swafe by Ishuah, maintained by piedcrow
Home-page: https://github.com/Radioafricagroup/swafe
Author: Joseph G.
Author-email: ndungugitau@gmail.com
License: GNU GPLv3
Keywords: aws-swf SWF
Platform: UNKNOWN
Classifier: Development Status :: 5 - Production/Stable
Classifier: License :: OSI Approved :: GNU General Public License v3 (GPLv3)
Classifier: Programming Language :: Python :: 2.7
Classifier: Programming Language :: Python :: 3.6
Classifier: Intended Audience :: Developers
Requires-Dist: boto3
Requires-Dist: click
Requires-Dist: future
